README.md
frasco_api.py
setup.py
frasco_api.egg-info/PKG-INFO
frasco_api.egg-info/SOURCES.txt
frasco_api.egg-info/dependency_links.txt
frasco_api.egg-info/not-zip-safe
frasco_api.egg-info/requires.txt
frasco_api.egg-info/top_level.txt