Metadata-Version: 1.0
Name: frasco-api
Version: 0.6.1
Summary: Create APIs and service based applications with Frasco
Home-page: http://github.com/frascoweb/frasco-api
Author: Maxime Bouroumeau-Fuseau
Author-email: maxime.bouroumeau@gmail.com
License: MIT
Platform: any
